rotten_tomatoes_scraper/__init__.py
rotten_tomatoes_scraper/rt_scraper.py
rotten_tomatoes_scraper/test_scraper.py
rotten_tomatoes_scraper-1.4.0.dist-info/LICENSE
rotten_tomatoes_scraper-1.4.0.dist-info/METADATA
rotten_tomatoes_scraper-1.4.0.dist-info/WHEEL
rotten_tomatoes_scraper-1.4.0.dist-info/entry_points.txt
rotten_tomatoes_scraper-1.4.0.dist-info/top_level.txt
rotten_tomatoes_scraper-1.4.0.dist-info/RECORD
