Metadata-Version: 2.1
Name: rotten-tomatoes-scraper
Version: 1.4.0
Summary: How to scrape Rotten Tomatoes website using an easy interface.
Home-page: https://github.com/pdrm83/rotten_tomatoes_scraper
Author: Pedram Ataee
Author-email: pedram.ataee@gmail.com
License: MIT
Platform: UNKNOWN
Classifier: License :: OSI Approved :: MIT License
Classifier: Programming Language :: Python :: 3
Classifier: Programming Language :: Python :: 3.7
License-File: LICENSE
Requires-Dist: bs4
Requires-Dist: requests
Requires-Dist: lxml
